{
  "name": "COTTON JACKET WITH POCKETS",
  "price": 199000,
  "discount": 60,
  "link": "https://www.zara.com/in/en/cotton-jacket-with-pockets-p09870460.html?v1=108971643"
}
{
  "name": "TAILORED WAISTCOAT",
  "price": 129000,
  "discount": 55,
  "link": "https://www.zara.com/in/en/tailored-waistcoat-p00761303.html?v1=116357554"
}
{
  "name": "LIGHTWEIGHT RUBBERISED JACKET",
  "price": 199000,
  "discount": 55,
  "link": "https://www.zara.com/in/en/lightweight-rubberised-jacket-p09621470.html?v1=108913959"
}
{
  "name": "KNIT VEST WITH HOOD",
  "price": 129000,
  "discount": 50,
  "link": "https://www.zara.com/in/en/knit-vest-with-hood-p09598301.html?v1=123919632"
}
{
  "name": "TEXTURED COTTON - LINEN TROUSERS",
  "price": 99000,
  "discount": 65,
  "link": "https://www.zara.com/in/en/textured-cotton---linen-trousers-p06861356.html?v1=115718792"
}
{
  "name": "QUILTED JACKET",
  "price": 199000,
  "discount": 60,
  "link": "https://www.zara.com/in/en/quilted-jacket-p04387301.html?v1=111912660"
}
{
  "name": "TEXTURED COTTON JACKET",
  "price": 249000,
  "discount": 60,
  "link": "https://www.zara.com/in/en/textured-cotton-jacket-p00706343.html?v1=129494714"
}
{
  "name": "TECHNICAL JACKET",
  "price": 199000,
  "discount": 55,
  "link": "https://www.zara.com/in/en/technical-jacket-p04432479.html?v1=108944911"
}
{
  "name": "COTTON BLEND POUCH POCKET PARKA",
  "price": 199000,
  "discount": 60,
  "link": "https://www.zara.com/in/en/cotton-blend-pouch-pocket-parka-p03918411.html?v1=108980438"
}
{
  "name": "COTTON CARDIGAN",
  "price": 129000,
  "discount": 70,
  "link": "https://www.zara.com/in/en/cotton-cardigan-p00761305.html?v1=114986667"
}
{
  "name": "TECHNICAL OVERSHIRT",
  "price": 199000,
  "discount": 30,
  "link": "https://www.zara.com/in/en/technical-overshirt-p08574360.html?v1=119862590"
}
{
  "name": "ZIPPED TRENCH COAT",
  "price": 199000,
  "discount": 75,
  "link": "https://www.zara.com/in/en/zipped-trench-coat-p05838104.html?v1=128357967"
}
{
  "name": "PHOTO PRINT SHIRT",
  "price": 99000,
  "discount": 65,
  "link": "https://www.zara.com/in/en/photo-print-shirt-p06380536.html?v1=131343731"
}
{
  "name": "ABSTRACT PRINT SHIRT",
  "price": 99000,
  "discount": 65,
  "link": "https://www.zara.com/in/en/abstract-print-shirt-p06379536.html?v1=131343732"
}
{
  "name": "PRINTED DENIM LASER PRINT VEST",
  "price": 99000,
  "discount": 75,
  "link": "https://www.zara.com/in/en/printed-denim-laser-print-vest-p00840309.html?v1=123838914"
}
{
  "name": "TEXTURED SHIRT",
  "price": 99000,
  "discount": 65,
  "link": "https://www.zara.com/in/en/textured-shirt-p00975302.html?v1=123838172"
}
{
  "name": "CHECK JACQUARD SCARF",
  "price": 59000,
  "discount": 70,
  "link": "https://www.zara.com/in/en/check-jacquard-scarf-p04204300.html?v1=142865566"
}
{
  "name": "JOGGER WAIST CORDUROY TROUSERS",
  "price": 99000,
  "discount": 75,
  "link": "https://www.zara.com/in/en/jogger-waist-corduroy-trousers-p04432480.html?v1=160942099"
}
{
  "name": "T-SHIRT WITH EMBROIDERED SLOGAN",
  "price": 39000,
  "discount": 75,
  "link": "https://www.zara.com/in/en/t-shirt-with-embroidered-slogan-p01887408.html?v1=128667016"
}
{
  "name": "T-SHIRT WITH EMBROIDERED SLOGAN",
  "price": 39000,
  "discount": 75,
  "link": "https://www.zara.com/in/en/t-shirt-with-embroidered-slogan-p01887408.html?v1=108988599"
}
{
  "name": "TEXTURED KNIT CARDIGAN",
  "price": 129000,
  "discount": 70,
  "link": "https://www.zara.com/in/en/textured-knit-cardigan-p05755314.html?v1=111677269"
}
{
  "name": "V-NECK KNIT VEST",
  "price": 79000,
  "discount": 70,
  "link": "https://www.zara.com/in/en/v-neck-knit-vest-p03332301.html?v1=123839582"
}
{
  "name": "V-NECK KNIT VEST",
  "price": 79000,
  "discount": 70,
  "link": "https://www.zara.com/in/en/v-neck-knit-vest-p03332301.html?v1=137550256"
}
{
  "name": "TEXTURED KNIT CARDIGAN",
  "price": 129000,
  "discount": 70,
  "link": "https://www.zara.com/in/en/textured-knit-cardigan-p05755314.html?v1=141539346"
}
{
  "name": "PLEATED CHINO TROUSERS",
  "price": 99000,
  "discount": 65,
  "link": "https://www.zara.com/in/en/pleated-chino-trousers-p02553309.html?v1=129271550"
}
{
  "name": "TEXTURED JOGGER WAIST TROUSERS",
  "price": 99000,
  "discount": 65,
  "link": "https://www.zara.com/in/en/textured-jogger-waist-trousers-p01300303.html?v1=124046503"
}
{
  "name": "QUILTED JACKET",
  "price": 199000,
  "discount": 60,
  "link": "https://www.zara.com/in/en/quilted-jacket-p04387301.html?v1=111912659"
}
{
  "name": "SET JACKET",
  "price": 199000,
  "discount": 60,
  "link": "https://www.zara.com/in/en/set-jacket-p00706451.html?v1=116322853"
}
{
  "name": "COTTON PLEATED TROUSERS",
  "price": 99000,
  "discount": 65,
  "link": "https://www.zara.com/in/en/cotton-pleated-trousers-p06861352.html?v1=111196319"
}
{
  "name": "PLEATED HERRINGBONE TROUSERS",
  "price": 99000,
  "discount": 65,
  "link": "https://www.zara.com/in/en/pleated-herringbone-trousers-p00647305.html?v1=128129508"
}
{
  "name": "OTTOMAN TROUSERS",
  "price": 99000,
  "discount": 65,
  "link": "https://www.zara.com/in/en/ottoman-trousers-p04087311.html?v1=124502111"
}
{
  "name": "COTTON PLEATED TROUSERS",
  "price": 99000,
  "discount": 65,
  "link": "https://www.zara.com/in/en/cotton-pleated-trousers-p06861352.html?v1=111196321"
}
{
  "name": "PLEATED CHINO TROUSERS",
  "price": 99000,
  "discount": 65,
  "link": "https://www.zara.com/in/en/pleated-chino-trousers-p06861372.html?v1=126513480"
}
{
  "name": "PLEATED CHINO TROUSERS",
  "price": 99000,
  "discount": 65,
  "link": "https://www.zara.com/in/en/pleated-chino-trousers-p06861306.html?v1=125044910"
}
{
  "name": "JOGGER WAIST COTTON TROUSERS",
  "price": 59000,
  "discount": 80,
  "link": "https://www.zara.com/in/en/jogger-waist-cotton-trousers-p00706342.html?v1=124046507"
}
{
  "name": "LINEN AND VISCOSE PLEATED TROUSERS",
  "price": 99000,
  "discount": 75,
  "link": "https://www.zara.com/in/en/linen-and-viscose-pleated-trousers-p09909455.html?v1=124502093"
}
{
  "name": "JOGGERS WITH PLEAT DETAIL",
  "price": 99000,
  "discount": 65,
  "link": "https://www.zara.com/in/en/joggers-with-pleat-detail-p05372313.html?v1=118121378"
}
{
  "name": "STRAIGHT FIT CHINO TROUSERS",
  "price": 99000,
  "discount": 65,
  "link": "https://www.zara.com/in/en/straight-fit-chino-trousers-p06917361.html?v1=121188310"
}
{
  "name": "TEXTURED WAIST JOGGER TROUSERS",
  "price": 99000,
  "discount": 65,
  "link": "https://www.zara.com/in/en/textured-waist-jogger-trousers-p06917332.html?v1=126718808"
}
{
  "name": "COLOURED SLIM FIT TROUSERS",
  "price": 99000,
  "discount": 60,
  "link": "https://www.zara.com/in/en/coloured-slim-fit-trousers-p09252320.html?v1=124902445"
}
{
  "name": "PLEATED LINEN TROUSERS",
  "price": 99000,
  "discount": 75,
  "link": "https://www.zara.com/in/en/pleated-linen-trousers-p00706301.html?v1=124501569"
}
{
  "name": "FADED-EFFECT T-SHIRT",
  "price": 59000,
  "discount": 60,
  "link": "https://www.zara.com/in/en/faded-effect-t-shirt-p00722445.html?v1=123838666"
}
{
  "name": "BASIC T-SHIRT WITH POCKET",
  "price": 59000,
  "discount": 65,
  "link": "https://www.zara.com/in/en/basic-t-shirt-with-pocket-p05372304.html?v1=124501391"
}
{
  "name": "DENIM JACKET",
  "price": 199000,
  "discount": 55,
  "link": "https://www.zara.com/in/en/denim-jacket-p02553312.html?v1=143566495"
}
{
  "name": "BASIC DENIM JACKET",
  "price": 199000,
  "discount": 30,
  "link": "https://www.zara.com/in/en/basic-denim-jacket-p01538313.html?v1=120440254"
}
{
  "name": "GEOMETRIC JACQUARD OVERSHIRT",
  "price": 199000,
  "discount": 60,
  "link": "https://www.zara.com/in/en/geometric-jacquard-overshirt-p03057204.html?v1=155211457"
}
{
  "name": "STRIPED BOMBER JACKET",
  "price": 199000,
  "discount": 55,
  "link": "https://www.zara.com/in/en/striped-bomber-jacket-p09632474.html?v1=129303633"
}
{
  "name": "TEXTURED COTTON PARKA",
  "price": 199000,
  "discount": 75,
  "link": "https://www.zara.com/in/en/textured-cotton-parka-p02675314.html?v1=122869282"
}
{
  "name": "JOGGING TROUSERS WITH STRIPE DETAIL",
  "price": 99000,
  "discount": 65,
  "link": "https://www.zara.com/in/en/jogging-trousers-with-stripe-detail-p04087342.html?v1=120162978"
}
{
  "name": "COLOUR BLOCK KNIT POLO WITH SLOGAN",
  "price": 129000,
  "discount": 55,
  "link": "https://www.zara.com/in/en/colour-block-knit-polo-with-slogan-p08689311.html?v1=111672966"
}
{
  "name": "LIGHTWEIGHT COTTON JACKET",
  "price": 199000,
  "discount": 55,
  "link": "https://www.zara.com/in/en/lightweight-cotton-jacket-p00706333.html?v1=108980494"
}
{
  "name": "FAUX LEATHER BIKER JACKET",
  "price": 199000,
  "discount": 60,
  "link": "https://www.zara.com/in/en/faux-leather-biker-jacket-p03427301.html?v1=109757278"
}
{
  "name": "TECHNICAL JACKET",
  "price": 199000,
  "discount": 55,
  "link": "https://www.zara.com/in/en/technical-jacket-p03918306.html?v1=115714621"
}
{
  "name": "TIE-DYE PRINT DENIM OVERSHIRT",
  "price": 129000,
  "discount": 55,
  "link": "https://www.zara.com/in/en/tie-dye-print-denim-overshirt-p07446303.html?v1=116774786"
}
{
  "name": "DOUBLE-FACED FAUX LEATHER JACKET",
  "price": 499000,
  "discount": 40,
  "link": "https://www.zara.com/in/en/double-faced-faux-leather-jacket-p00706316.html?v1=120406537"
}
{
  "name": "CORDUROY POLO SHIRT",
  "price": 99000,
  "discount": 65,
  "link": "https://www.zara.com/in/en/corduroy-polo-shirt-p08779401.html?v1=142447980"
}
{
  "name": "WAXED WORKER OVERSHIRT",
  "price": 129000,
  "discount": 70,
  "link": "https://www.zara.com/in/en/waxed-worker-overshirt-p09621310.html?v1=108979896"
}
{
  "name": "RELAXED SET OVERSHIRT",
  "price": 129000,
  "discount": 70,
  "link": "https://www.zara.com/in/en/relaxed-set-overshirt-p03562403.html?v1=125045084"
}
{
  "name": "® ERIN WILSON PATCH OVERSHIRT",
  "price": 199000,
  "discount": 60,
  "link": "https://www.zara.com/in/en/%C2%AE-erin-wilson-patch-overshirt-p05950515.html?v1=137086170"
}
{
  "name": "BASIC QUILTED JACKET",
  "price": 199000,
  "discount": 60,
  "link": "https://www.zara.com/in/en/basic-quilted-jacket-p03918307.html?v1=164118374"
}
{
  "name": "PUFFER GILET",
  "price": 99000,
  "discount": 60,
  "link": "https://www.zara.com/in/en/puffer-gilet-p08574370.html?v1=120986218"
}
{
  "name": "COTTON - HEMP SHIRT",
  "price": 99000,
  "discount": 65,
  "link": "https://www.zara.com/in/en/cotton---hemp-shirt-p08727302.html?v1=125068601"
}
{
  "name": "TIE-DYE SOFT DENIM TROUSERS",
  "price": 99000,
  "discount": 65,
  "link": "https://www.zara.com/in/en/tie-dye-soft-denim-trousers-p05862338.html?v1=134158012"
}
{
  "name": "OVERSHIRT WITH POCKETS",
  "price": 129000,
  "discount": 70,
  "link": "https://www.zara.com/in/en/overshirt-with-pockets-p00072927.html?v1=126744688"
}
{
  "name": "COTTON TRENCH COAT",
  "price": 199000,
  "discount": 75,
  "link": "https://www.zara.com/in/en/cotton-trench-coat-p09621321.html?v1=109748919"
}
{
  "name": "CONTRAST SLOGAN SHIRT",
  "price": 99000,
  "discount": 65,
  "link": "https://www.zara.com/in/en/contrast-slogan-shirt-p03717350.html?v1=120425567"
}
{
  "name": "CONTRAST COLLAR JACKET",
  "price": 129000,
  "discount": 80,
  "link": "https://www.zara.com/in/en/contrast-collar-jacket-p05320305.html?v1=113754492"
}
{
  "name": "CARROT FIT TROUSERS",
  "price": 99000,
  "discount": 65,
  "link": "https://www.zara.com/in/en/carrot-fit-trousers-p09632306.html?v1=124902451"
}
{
  "name": "CONTRAST ZIP-UP SWEATSHIRT",
  "price": 129000,
  "discount": 55,
  "link": "https://www.zara.com/in/en/contrast-zip-up-sweatshirt-p05372325.html?v1=137547701"
}
{
  "name": "WATER-REPELLENT DOWN PUFFER JACKET",
  "price": 499000,
  "discount": 40,
  "link": "https://www.zara.com/in/en/water-repellent-down-puffer-jacket-p03427420.html?v1=133387090"
}
{
  "name": "COMFORT TEXTURED BLAZER",
  "price": 199000,
  "discount": 60,
  "link": "https://www.zara.com/in/en/comfort-textured-blazer-p06861350.html?v1=111313096"
}
{
  "name": "BASIC DENIM JACKET",
  "price": 199000,
  "discount": 30,
  "link": "https://www.zara.com/in/en/basic-denim-jacket-p04454450.html?v1=123919509"
}
{
  "name": "SEERSUCKER BOMBER JACKET",
  "price": 199000,
  "discount": 55,
  "link": "https://www.zara.com/in/en/seersucker-bomber-jacket-p03918302.html?v1=123919525"
}
{
  "name": "ANIMAL PRINT JACKET",
  "price": 199000,
  "discount": 60,
  "link": "https://www.zara.com/in/en/animal-print-jacket-p04164300.html?v1=144686742"
}
{
  "name": "PLEATED CHINO TROUSERS",
  "price": 99000,
  "discount": 65,
  "link": "https://www.zara.com/in/en/pleated-chino-trousers-p06861311.html?v1=131204224"
}
{
  "name": "RUNNING GILET",
  "price": 99000,
  "discount": 75,
  "link": "https://www.zara.com/in/en/running-gilet-p01591400.html?v1=109653237"
}
{
  "name": "COMBINED KNIT T-SHIRT",
  "price": 79000,
  "discount": 70,
  "link": "https://www.zara.com/in/en/combined-knit-t-shirt-p06674300.html?v1=126358198"
}
{
  "name": "STRIPED T-SHIRT",
  "price": 59000,
  "discount": 70,
  "link": "https://www.zara.com/in/en/striped-t-shirt-p00722314.html?v1=124525193"
}
{
  "name": "PACKABLE SEERSUCKER SUIT TROUSERS",
  "price": 99000,
  "discount": 65,
  "link": "https://www.zara.com/in/en/packable-seersucker-suit-trousers-p09870411.html?v1=123838980"
}
{
  "name": "UTILITY JACKET",
  "price": 199000,
  "discount": 60,
  "link": "https://www.zara.com/in/en/utility-jacket-p01105302.html?v1=108989530"
}
{
  "name": "TECHNICAL JACKET",
  "price": 199000,
  "discount": 55,
  "link": "https://www.zara.com/in/en/technical-jacket-p03918306.html?v1=115714619"
}
{
  "name": "ANIMAL PRINT JACKET",
  "price": 199000,
  "discount": 60,
  "link": "https://www.zara.com/in/en/animal-print-jacket-p04164301.html?v1=128353363"
}
{
  "name": "COTTON - LINEN BOMBER JACKET",
  "price": 199000,
  "discount": 55,
  "link": "https://www.zara.com/in/en/cotton---linen-bomber-jacket-p01564380.html?v1=142882818"
}
{
  "name": "HOODED TECHNICAL JACKET",
  "price": 199000,
  "discount": 55,
  "link": "https://www.zara.com/in/en/hooded-technical-jacket-p08281507.html?v1=144305813"
}
{
  "name": "LIGHTWEIGHT PUFFER GILET",
  "price": 99000,
  "discount": 65,
  "link": "https://www.zara.com/in/en/lightweight-puffer-gilet-p04317301.html?v1=108927564"
}
{
  "name": "STRIPED COTTON SHIRT",
  "price": 99000,
  "discount": 65,
  "link": "https://www.zara.com/in/en/striped-cotton-shirt-p05588404.html?v1=116118475"
}
{
  "name": "STRIPED SHIRT",
  "price": 99000,
  "discount": 65,
  "link": "https://www.zara.com/in/en/striped-shirt-p07545275.html?v1=125067534"
}
{
  "name": "STRIPED TAILORED SHIRT",
  "price": 99000,
  "discount": 65,
  "link": "https://www.zara.com/in/en/striped-tailored-shirt-p00975405.html?v1=125170016"
}
{
  "name": "PRINTED SLOGAN SWEATSHIRT",
  "price": 129000,
  "discount": 50,
  "link": "https://www.zara.com/in/en/printed-slogan-sweatshirt-p00977305.html?v1=150946478"
}
{
  "name": "COLOUR BLOCK JOGGER TROUSERS",
  "price": 99000,
  "discount": 65,
  "link": "https://www.zara.com/in/en/colour-block-jogger-trousers-p00761342.html?v1=123657699"
}
{
  "name": "EMBROIDERED SLOGAN T-SHIRT",
  "price": 59000,
  "discount": 60,
  "link": "https://www.zara.com/in/en/embroidered-slogan-t-shirt-p06224311.html?v1=125044932"
}
{
  "name": "JACKET",
  "price": 199000,
  "discount": 60,
  "link": "https://www.zara.com/in/en/jacket-p00706450.html?v1=108911610"
}
{
  "name": "TEXTURED BOMBER JACKET",
  "price": 199000,
  "discount": 30,
  "link": "https://www.zara.com/in/en/textured-bomber-jacket-p01104300.html?v1=108939040"
}
{
  "name": "STRIPED JACQUARD OVERSHIRT",
  "price": 199000,
  "discount": 60,
  "link": "https://www.zara.com/in/en/striped-jacquard-overshirt-p02675308.html?v1=116154706"
}
{
  "name": "QUILTED BOMBER JACKET",
  "price": 199000,
  "discount": 30,
  "link": "https://www.zara.com/in/en/quilted-bomber-jacket-p08574560.html?v1=121258631"
}
{
  "name": "BASIC BERMUDA SHORTS",
  "price": 59000,
  "discount": 80,
  "link": "https://www.zara.com/in/en/basic-bermuda-shorts-p05719137.html?v1=124525285"
}
{
  "name": "STRIPED PRINT SHIRT",
  "price": 79000,
  "discount": 70,
  "link": "https://www.zara.com/in/en/striped-print-shirt-p06987432.html?v1=108929342"
}
{
  "name": "BASIC T-SHIRT",
  "price": 59000,
  "discount": 70,
  "link": "https://www.zara.com/in/en/basic-t-shirt-p00722303.html?v1=110606803"
}
{
  "name": "WOOL - SILK SWEATER",
  "price": 129000,
  "discount": 70,
  "link": "https://www.zara.com/in/en/wool---silk-sweater-p02893306.html?v1=122688109"
}
{
  "name": "SHORT SLEEVE HOODIE",
  "price": 129000,
  "discount": 45,
  "link": "https://www.zara.com/in/en/short-sleeve-hoodie-p04087464.html?v1=123838603"
}
{
  "name": "PREMIUM HOODED PARKA",
  "price": 129000,
  "discount": 75,
  "link": "https://www.zara.com/in/en/premium-hooded-parka-p04087358.html?v1=129691760"
}
{
  "name": "STRIPED SHIRT WITH TOPSTITCHING",
  "price": 99000,
  "discount": 65,
  "link": "https://www.zara.com/in/en/striped-shirt-with-topstitching-p03562306.html?v1=115710053"
}
{
  "name": "PACKABLE SEERSUCKER SUIT TROUSERS",
  "price": 99000,
  "discount": 65,
  "link": "https://www.zara.com/in/en/packable-seersucker-suit-trousers-p09870411.html?v1=123837996"
}
{
  "name": "HERRINGBONE TEXTURED SHIRT",
  "price": 99000,
  "discount": 65,
  "link": "https://www.zara.com/in/en/herringbone-textured-shirt-p07545363.html?v1=138862855"
}
{
  "name": "SLOGAN PRINT T-SHIRT",
  "price": 59000,
  "discount": 70,
  "link": "https://www.zara.com/in/en/slogan-print-t-shirt-p06224410.html?v1=123266604"
}
{
  "name": "LONG LENGTH T-SHIRT",
  "price": 59000,
  "discount": 60,
  "link": "https://www.zara.com/in/en/long-length-t-shirt-p01887300.html?v1=123839703"
}
{
  "name": "BASIC T-SHIRT",
  "price": 59000,
  "discount": 70,
  "link": "https://www.zara.com/in/en/basic-t-shirt-p00722303.html?v1=110606801"
}
{
  "name": "SLIM FIT JOGGING TROUSERS",
  "price": 99000,
  "discount": 50,
  "link": "https://www.zara.com/in/en/slim-fit-jogging-trousers-p04087325.html?v1=124501582"
}
{
  "name": "BASIC QUILTED JACKET",
  "price": 199000,
  "discount": 60,
  "link": "https://www.zara.com/in/en/basic-quilted-jacket-p03918307.html?v1=115710024"
}
{
  "name": "COTTON - LINEN BOMBER JACKET",
  "price": 199000,
  "discount": 55,
  "link": "https://www.zara.com/in/en/cotton---linen-bomber-jacket-p01564380.html?v1=125044533"
}
{
  "name": "PARKA WITH CONTRAST COLLAR",
  "price": 199000,
  "discount": 75,
  "link": "https://www.zara.com/in/en/parka-with-contrast-collar-p07484379.html?v1=144686910"
}
{
  "name": "COTTON - LINEN SHIRT",
  "price": 99000,
  "discount": 65,
  "link": "https://www.zara.com/in/en/cotton---linen-shirt-p02688400.html?v1=112923916"
}
{
  "name": "LYOCELL - COTTON SHIRT WITH POCKETS",
  "price": 99000,
  "discount": 65,
  "link": "https://www.zara.com/in/en/lyocell---cotton-shirt-with-pockets-p06048402.html?v1=124908120"
}
{
  "name": "SLIM FIT JEANS",
  "price": 99000,
  "discount": 60,
  "link": "https://www.zara.com/in/en/slim-fit-jeans-p00647400.html?v1=125045357"
}
{
  "name": "TEXTURED SHIRT",
  "price": 99000,
  "discount": 65,
  "link": "https://www.zara.com/in/en/textured-shirt-p00072496.html?v1=144686718"
}
{
  "name": "GEOMETRIC PRINT POLO SHIRT",
  "price": 59000,
  "discount": 70,
  "link": "https://www.zara.com/in/en/geometric-print-polo-shirt-p04161303.html?v1=121193413"
}
{
  "name": "FADED OVERSHIRT",
  "price": 129000,
  "discount": 55,
  "link": "https://www.zara.com/in/en/faded-overshirt-p07446360.html?v1=128129505"
}
{
  "name": "PACKABLE SEERSUCKER SUIT TROUSERS",
  "price": 99000,
  "discount": 65,
  "link": "https://www.zara.com/in/en/packable-seersucker-suit-trousers-p09870411.html?v1=124502416"
}
{
  "name": "COTTON SHIRT WITH POCKET",
  "price": 99000,
  "discount": 65,
  "link": "https://www.zara.com/in/en/cotton-shirt-with-pocket-p05588402.html?v1=110608927"
}
{
  "name": "FLORAL PRINT SHIRT",
  "price": 99000,
  "discount": 65,
  "link": "https://www.zara.com/in/en/floral-print-shirt-p05695281.html?v1=120689755"
}
{
  "name": "LYOCELL AND COTTON SHIRT",
  "price": 99000,
  "discount": 65,
  "link": "https://www.zara.com/in/en/lyocell-and-cotton-shirt-p07545489.html?v1=122520395"
}
{
  "name": "CHECK FLANNEL SHIRT",
  "price": 99000,
  "discount": 75,
  "link": "https://www.zara.com/in/en/check-flannel-shirt-p07446308.html?v1=126564400"
}
{
  "name": "TEXTURED SHIRT",
  "price": 99000,
  "discount": 65,
  "link": "https://www.zara.com/in/en/textured-shirt-p00072496.html?v1=126744681"
}
{
  "name": "TEXTURED CHECK WAISTCOAT",
  "price": 99000,
  "discount": 75,
  "link": "https://www.zara.com/in/en/textured-check-waistcoat-p03057320.html?v1=130679475"
}
{
  "name": "OXFORD SHIRT",
  "price": 99000,
  "discount": 65,
  "link": "https://www.zara.com/in/en/oxford-shirt-p05588420.html?v1=131383809"
}
{
  "name": "KNIT COTTON POLO SHIRT",
  "price": 129000,
  "discount": 55,
  "link": "https://www.zara.com/in/en/knit-cotton-polo-shirt-p02632309.html?v1=114490886"
}
{
  "name": "TIE-DYE PRINT DENIM OVERSHIRT",
  "price": 129000,
  "discount": 55,
  "link": "https://www.zara.com/in/en/tie-dye-print-denim-overshirt-p07446303.html?v1=129531460"
}
{
  "name": "OVERSHIRT WITH POCKETS",
  "price": 129000,
  "discount": 70,
  "link": "https://www.zara.com/in/en/overshirt-with-pockets-p05722137.html?v1=135327193"
}
{
  "name": "STRIPED KNIT POLO SHIRT",
  "price": 129000,
  "discount": 55,
  "link": "https://www.zara.com/in/en/striped-knit-polo-shirt-p00693414.html?v1=137549689"
}
{
  "name": "VELVET SWEATSHIRT",
  "price": 129000,
  "discount": 50,
  "link": "https://www.zara.com/in/en/velvet-sweatshirt-p04087309.html?v1=156797362"
}
{
  "name": "KNIT T-SHIRT",
  "price": 79000,
  "discount": 55,
  "link": "https://www.zara.com/in/en/knit-t-shirt-p04231400.html?v1=145004984"
}
{
  "name": "TEXTURED BERMUDA SHORTS",
  "price": 59000,
  "discount": 75,
  "link": "https://www.zara.com/in/en/textured-bermuda-shorts-p02649452.html?v1=124501592"
}
{
  "name": "PACKABLE SEERSUCKER SUIT TROUSERS",
  "price": 99000,
  "discount": 65,
  "link": "https://www.zara.com/in/en/packable-seersucker-suit-trousers-p09870411.html?v1=127774413"
}
{
  "name": "CHECK SUIT BLAZER",
  "price": 199000,
  "discount": 75,
  "link": "https://www.zara.com/in/en/check-suit-blazer-p00706262.html?v1=123837941"
}
{
  "name": "SET BLAZER",
  "price": 199000,
  "discount": 75,
  "link": "https://www.zara.com/in/en/set-blazer-p00706424.html?v1=137231981"
}
{
  "name": "COMFORT SUIT BLAZER",
  "price": 199000,
  "discount": 75,
  "link": "https://www.zara.com/in/en/comfort-suit-blazer-p01564356.html?v1=137548719"
}
{
  "name": "TEXTURED BOMBER JACKET",
  "price": 199000,
  "discount": 30,
  "link": "https://www.zara.com/in/en/textured-bomber-jacket-p01104300.html?v1=151035814"
}
{
  "name": "CHECK OVERSHIRT",
  "price": 199000,
  "discount": 60,
  "link": "https://www.zara.com/in/en/check-overshirt-p02675404.html?v1=155211471"
}
{
  "name": "SLOGAN PRINT SHIRT",
  "price": 99000,
  "discount": 65,
  "link": "https://www.zara.com/in/en/slogan-print-shirt-p06085340.html?v1=120417452"
}
{
  "name": "TAPERED SKINNY JEANS",
  "price": 99000,
  "discount": 65,
  "link": "https://www.zara.com/in/en/tapered-skinny-jeans-p00840375.html?v1=120689860"
}
{
  "name": "CONTRAST SLOGAN T-SHIRT",
  "price": 59000,
  "discount": 70,
  "link": "https://www.zara.com/in/en/contrast-slogan-t-shirt-p00962392.html?v1=117768218"
}
{
  "name": "PIQUÉ TEXTURE T-SHIRT",
  "price": 59000,
  "discount": 60,
  "link": "https://www.zara.com/in/en/piqu%C3%A9-texture-t-shirt-p06462301.html?v1=124501833"
}
{
  "name": "FLORAL PRINT JEANS",
  "price": 99000,
  "discount": 75,
  "link": "https://www.zara.com/in/en/floral-print-jeans-p00840385.html?v1=123051033"
}
{
  "name": "STRAIGHT FIT JEANS WITH VENTS",
  "price": 99000,
  "discount": 75,
  "link": "https://www.zara.com/in/en/straight-fit-jeans-with-vents-p00840322.html?v1=129271522"
}
{
  "name": "LINEN - COTTON BERMUDA SHORTS",
  "price": 59000,
  "discount": 75,
  "link": "https://www.zara.com/in/en/linen---cotton-bermuda-shorts-p06861404.html?v1=124502123"
}
{
  "name": "BASIC T-SHIRT WITH POCKET",
  "price": 59000,
  "discount": 65,
  "link": "https://www.zara.com/in/en/basic-t-shirt-with-pocket-p05372304.html?v1=124525596"
}
{
  "name": "BASIC POLO SHIRT",
  "price": 59000,
  "discount": 70,
  "link": "https://www.zara.com/in/en/basic-polo-shirt-p09240305.html?v1=117778392"
}
{
  "name": "PREMIUM T-SHIRT WITH POCKET",
  "price": 59000,
  "discount": 70,
  "link": "https://www.zara.com/in/en/premium-t-shirt-with-pocket-p04087352.html?v1=126436098"
}
{
  "name": "STRIPED KNIT POLO SHIRT",
  "price": 129000,
  "discount": 55,
  "link": "https://www.zara.com/in/en/striped-knit-polo-shirt-p00693414.html?v1=108911208"
}
{
  "name": "BASIC SWEATSHIRT",
  "price": 129000,
  "discount": 50,
  "link": "https://www.zara.com/in/en/basic-sweatshirt-p05372301.html?v1=124500739"
}
{
  "name": "T-SHIRT WITH EMBROIDERED SLOGAN",
  "price": 59000,
  "discount": 65,
  "link": "https://www.zara.com/in/en/t-shirt-with-embroidered-slogan-p06224316.html?v1=108944746"
}
{
  "name": "JOGGER WAIST BERMUDA SHORTS",
  "price": 59000,
  "discount": 75,
  "link": "https://www.zara.com/in/en/jogger-waist-bermuda-shorts-p06917414.html?v1=123416105"
}
{
  "name": "BASIC JOGGING TROUSERS",
  "price": 99000,
  "discount": 60,
  "link": "https://www.zara.com/in/en/basic-jogging-trousers-p00526325.html?v1=114486642"
}
{
  "name": "CONTRAST PRINT SHIRT",
  "price": 99000,
  "discount": 65,
  "link": "https://www.zara.com/in/en/contrast-print-shirt-p03057111.html?v1=121193410"
}
{
  "name": "PRINTED SEERSUCKER SHIRT",
  "price": 79000,
  "discount": 70,
  "link": "https://www.zara.com/in/en/printed-seersucker-shirt-p07380400.html?v1=123838180"
}
{
  "name": "CREASED-EFFECT SHIRT",
  "price": 79000,
  "discount": 65,
  "link": "https://www.zara.com/in/en/creased-effect-shirt-p06103401.html?v1=123839173"
}
{
  "name": "LYOCELL - COTTON SHIRT WITH POCKETS",
  "price": 99000,
  "discount": 65,
  "link": "https://www.zara.com/in/en/lyocell---cotton-shirt-with-pockets-p06048402.html?v1=124908122"
}
{
  "name": "LYOCELL - COTTON SHIRT WITH POCKETS",
  "price": 99000,
  "discount": 65,
  "link": "https://www.zara.com/in/en/lyocell---cotton-shirt-with-pockets-p06048402.html?v1=137547635"
}
{
  "name": "LYOCELL - COTTON SHIRT WITH POCKETS",
  "price": 99000,
  "discount": 65,
  "link": "https://www.zara.com/in/en/lyocell---cotton-shirt-with-pockets-p06048402.html?v1=137551107"
}
{
  "name": "FLANNEL SHIRT WITH POCKET",
  "price": 99000,
  "discount": 60,
  "link": "https://www.zara.com/in/en/flannel-shirt-with-pocket-p07545372.html?v1=140384392"
}
{
  "name": "COTTON SHIRT",
  "price": 99000,
  "discount": 75,
  "link": "https://www.zara.com/in/en/cotton-shirt-p06580553.html?v1=141267800"
}
{
  "name": "TEXTURED COTTON SHIRT",
  "price": 99000,
  "discount": 65,
  "link": "https://www.zara.com/in/en/textured-cotton-shirt-p06592611.html?v1=143354387"
}
{
  "name": "GEOMETRIC JACQUARD QUILTED WAISTCOAT",
  "price": 99000,
  "discount": 75,
  "link": "https://www.zara.com/in/en/geometric-jacquard-quilted-waistcoat-p03918313.html?v1=156797306"
}
{
  "name": "POLAR FLEECE JOGGING TROUSERS",
  "price": 99000,
  "discount": 65,
  "link": "https://www.zara.com/in/en/polar-fleece-jogging-trousers-p08574355.html?v1=160942618"
}
{
  "name": "STRIPED COTTON SHIRT",
  "price": 79000,
  "discount": 70,
  "link": "https://www.zara.com/in/en/striped-cotton-shirt-p05588413.html?v1=122558264"
}
{
  "name": "FLOWING KNIT T-SHIRT",
  "price": 79000,
  "discount": 60,
  "link": "https://www.zara.com/in/en/flowing-knit-t-shirt-p04231402.html?v1=123837553"
}
{
  "name": "SLOGAN PRINT T-SHIRT",
  "price": 59000,
  "discount": 70,
  "link": "https://www.zara.com/in/en/slogan-print-t-shirt-p00495302.html?v1=125068538"
}
{
  "name": "PAINT SPLATTER PRINT T-SHIRT",
  "price": 59000,
  "discount": 70,
  "link": "https://www.zara.com/in/en/paint-splatter-print-t-shirt-p00495442.html?v1=108980106"
}
{
  "name": "CORDUROY OVERSHIRT",
  "price": 129000,
  "discount": 55,
  "link": "https://www.zara.com/in/en/corduroy-overshirt-p01123350.html?v1=111498797"
}
{
  "name": "EASY CARE TEXTURED SHIRT",
  "price": 99000,
  "discount": 50,
  "link": "https://www.zara.com/in/en/easy-care-textured-shirt-p07545416.html?v1=112907103"
}
{
  "name": "HIGH NECK SWEATER WITH ZIP",
  "price": 129000,
  "discount": 55,
  "link": "https://www.zara.com/in/en/high-neck-sweater-with-zip-p00632310.html?v1=115735591"
}
{
  "name": "CONTRAST PRINT T-SHIRT",
  "price": 59000,
  "discount": 65,
  "link": "https://www.zara.com/in/en/contrast-print-t-shirt-p00962307.html?v1=123837899"
}
{
  "name": "PAINT SPLATTER PRINT T-SHIRT",
  "price": 59000,
  "discount": 70,
  "link": "https://www.zara.com/in/en/paint-splatter-print-t-shirt-p00495442.html?v1=123839160"
}
{
  "name": "CONTRAST PRINT T-SHIRT",
  "price": 59000,
  "discount": 65,
  "link": "https://www.zara.com/in/en/contrast-print-t-shirt-p00962307.html?v1=123839731"
}
{
  "name": "STRIPED CREASED-EFFECT SHIRT",
  "price": 79000,
  "discount": 65,
  "link": "https://www.zara.com/in/en/striped-creased-effect-shirt-p01413400.html?v1=124502052"
}
{
  "name": "PIQUÉ TEXTURE T-SHIRT",
  "price": 59000,
  "discount": 60,
  "link": "https://www.zara.com/in/en/piqu%C3%A9-texture-t-shirt-p06462301.html?v1=124502365"
}
{
  "name": "PIQUÉ TEXTURE T-SHIRT",
  "price": 59000,
  "discount": 60,
  "link": "https://www.zara.com/in/en/piqu%C3%A9-texture-t-shirt-p06462301.html?v1=124525581"
}
{
  "name": "STRIPED KNIT POLO SHIRT",
  "price": 129000,
  "discount": 55,
  "link": "https://www.zara.com/in/en/striped-knit-polo-shirt-p00693414.html?v1=137547686"
}
{
  "name": "TEXTURED SUIT BLAZER",
  "price": 199000,
  "discount": 75,
  "link": "https://www.zara.com/in/en/textured-suit-blazer-p05930294.html?v1=137551212"
}
{
  "name": "KNIT COTTON POLO SHIRT",
  "price": 129000,
  "discount": 55,
  "link": "https://www.zara.com/in/en/knit-cotton-polo-shirt-p02632309.html?v1=139866298"
}
{
  "name": "LIMITED EDITION WOOL JACKET",
  "price": 199000,
  "discount": 85,
  "link": "https://www.zara.com/in/en/limited-edition-wool-jacket-p05917038.html?v1=151898779"
}
